veiled/__init__.py
veiled/cli.py
veiled-0.2.4.dist-info/entry_points.txt
veiled-0.2.4.dist-info/LICENSE
veiled-0.2.4.dist-info/WHEEL
veiled-0.2.4.dist-info/METADATA
veiled-0.2.4.dist-info/RECORD
