Metadata-Version: 2.1
Name: veiled
Version: 0.2.4
Summary: A very thin CLI wrapper around cryptography.fernet:Fernet
License: MIT
Keywords: encryption,symmetric,commandline
Author: Vasili Syrakis
Author-email: cetanu@gmail.com
Requires-Python: >=3.7,<4.0
Classifier: License :: OSI Approved :: MIT License
Classifier: Programming Language :: Python :: 3
Classifier: Programming Language :: Python :: 3.7
Classifier: Programming Language :: Python :: 3.8
Classifier: Programming Language :: Python :: 3.9
Requires-Dist: PyYAML (>=6.0,<7.0)
Requires-Dist: cryptography (>=36.0.1,<37.0.0)
Requires-Dist: typer (>=0.4.0,<0.5.0)
